mx_logger/__init__.py
mx_logger/logger.py
mx_logger-1.0.0.dist-info/METADATA
mx_logger-1.0.0.dist-info/WHEEL
mx_logger-1.0.0.dist-info/RECORD
