Metadata-Version: 2.3
Name: mx-logger
Version: 1.0.0
Summary: mx logger
Author: oevergodofchaos
Author-email: vezonzzzzzz@gmail.com
Requires-Python: >=3.11
Classifier: Programming Language :: Python :: 3
Classifier: Programming Language :: Python :: 3.11
Classifier: Programming Language :: Python :: 3.12
Classifier: Programming Language :: Python :: 3.13
